LICENSE
LICENSE.txt
README.rst
setup.cfg
setup.py
hotlatta/__init__.py
hotlatta/hotlatta.py
hotlatta.egg-info/PKG-INFO
hotlatta.egg-info/SOURCES.txt
hotlatta.egg-info/dependency_links.txt
hotlatta.egg-info/top_level.txt